twat_cache/__init__.py
twat_cache/__main__.py
twat_cache/backend_selector.py
twat_cache/cache.py
twat_cache/config.py
twat_cache/context.py
twat_cache/decorators.py
twat_cache/exceptions.py
twat_cache/hybrid_cache.py
twat_cache/logging.py
twat_cache/paths.py
twat_cache/py.typed
twat_cache/type_defs.py
twat_cache/utils.py
twat_cache/engines/__init__.py
twat_cache/engines/aiocache.py
twat_cache/engines/base.py
twat_cache/engines/cachebox.py
twat_cache/engines/cachetools.py
twat_cache/engines/common.py
twat_cache/engines/diskcache.py
twat_cache/engines/functools.py
twat_cache/engines/functools_engine.py
twat_cache/engines/joblib.py
twat_cache/engines/klepto.py
twat_cache/engines/manager.py
twat_cache/engines/py.typed
twat_cache/engines/redis.py
twat_cache/types/cachebox.pyi
twat_cache-2.7.5.dist-info/METADATA
twat_cache-2.7.5.dist-info/WHEEL
twat_cache-2.7.5.dist-info/entry_points.txt
twat_cache-2.7.5.dist-info/licenses/LICENSE
twat_cache-2.7.5.dist-info/RECORD
