Metadata-Version: 2.4
Name: twat-cache
Version: 2.7.5
Summary: Advanced caching library for Python, part of the twat framework
Project-URL: Documentation, https://github.com/twardoch/twat/tree/main/docs
Project-URL: Issues, https://github.com/twardoch/twat/issues
Project-URL: Source, https://github.com/twardoch/twat
Author-email: Adam Twardoch <adam+github@twardoch.com>
License-Expression: MIT
License-File: LICENSE
Keywords: cache,caching,memorization,optimization,performance
Classifier: Development Status :: 4 - Beta
Classifier: Programming Language :: Python
Classifier: Programming Language :: Python :: 3.10
Classifier: Programming Language :: Python :: 3.11
Classifier: Programming Language :: Python :: 3.12
Classifier: Programming Language :: Python :: Implementation :: CPython
Classifier: Programming Language :: Python :: Implementation :: PyPy
Requires-Python: >=3.10
Requires-Dist: cachetools>=5.3.2
Requires-Dist: diskcache>=5.6.1
Requires-Dist: joblib>=1.3.2
Requires-Dist: loguru>=0.7.0
Requires-Dist: pydantic>=2.0
Provides-Extra: all
Requires-Dist: aiocache>=0.12.3; extra == 'all'
Requires-Dist: cachebox>=4.5.1; extra == 'all'
Requires-Dist: cachetools>=5.5.1; extra == 'all'
Requires-Dist: diskcache>=5.6.3; extra == 'all'
Requires-Dist: joblib>=1.4.2; extra == 'all'
Requires-Dist: klepto>=0.2.6; extra == 'all'
Requires-Dist: platformdirs>=4.3.6; extra == 'all'
Provides-Extra: dev
Requires-Dist: pre-commit>=3.6.0; extra == 'dev'
Provides-Extra: test
Requires-Dist: pytest-benchmark[histogram]>=4.0.0; extra == 'test'
Requires-Dist: pytest-cov>=4.0.0; extra == 'test'
Requires-Dist: pytest-xdist>=3.5.0; extra == 'test'
Requires-Dist: pytest>=7.0.0; extra == 'test'
